<annotation>
	<folder>simple</folder>
	<filename>02903.jpg</filename>
	<source>
		<database>The simple Database</database>
		<annotation>simple</annotation>
		<image>flickr</image>
		<flickrid>325991873</flickrid>
	</source>
	<owner>
		<flickrid>archin</flickrid>
		<name>?</name>
	</owner>
	<size>
		<width>1280</width>
		<height>720</height>
		<depth>3</depth>
	</size>
	<segmented>0</segmented>
	<object>
		<name>prohibitory</name>
		<pose>Unspecified</pose>
		<truncated>0</truncated>
		<difficult>0</difficult>
		<bndbox>
			<xmin>1140</xmin>
			<ymin>360</ymin>
			<xmax>1206</xmax>
			<ymax>423</ymax>
		</bndbox>
	</object>
	<object>
		<name>mandatory</name>
		<pose>Unspecified</pose>
		<truncated>0</truncated>
		<difficult>0</difficult>
		<bndbox>
			<xmin>1136</xmin>
			<ymin>425</ymin>
			<xmax>1204</xmax>
			<ymax>487</ymax>
		</bndbox>
	</object>
</annotation>