<annotation verified="no">
  <folder>images</folder>
  <filename>03665</filename>
  <path>J:\360\sunny\images\03665.png</path>
  <source>
    <database>Unknown</database>
  </source>
  <size>
    <width>848</width>
    <height>480</height>
    <depth>3</depth>
  </size>
  <segmented>0</segmented>
  <object>
    <name>warning</name>
    <pose>Unspecified</pose>
    <truncated>0</truncated>
    <Difficult>0</Difficult>
    <bndbox>
      <xmin>509</xmin>
      <ymin>130</ymin>
      <xmax>568</xmax>
      <ymax>188</ymax>
    </bndbox>
  </object>
  <object>
    <name>prohibitory</name>
    <pose>Unspecified</pose>
    <truncated>0</truncated>
    <Difficult>0</Difficult>
    <bndbox>
      <xmin>454</xmin>
      <ymin>217</ymin>
      <xmax>466</xmax>
      <ymax>232</ymax>
    </bndbox>
  </object>
  <object>
    <name>prohibitory</name>
    <pose>Unspecified</pose>
    <truncated>0</truncated>
    <Difficult>0</Difficult>
    <bndbox>
      <xmin>453</xmin>
      <ymin>234</ymin>
      <xmax>466</xmax>
      <ymax>247</ymax>
    </bndbox>
  </object>
</annotation>
