<annotation verified="no">
  <folder>images</folder>
  <filename>04717</filename>
  <path>J:\360\sunny\images\04717.png</path>
  <source>
    <database>Unknown</database>
  </source>
  <size>
    <width>848</width>
    <height>480</height>
    <depth>3</depth>
  </size>
  <segmented>0</segmented>
  <object>
    <name>prohibitory</name>
    <pose>Unspecified</pose>
    <truncated>0</truncated>
    <Difficult>0</Difficult>
    <bndbox>
      <xmin>638</xmin>
      <ymin>125</ymin>
      <xmax>664</xmax>
      <ymax>166</ymax>
    </bndbox>
  </object>
  <object>
    <name>prohibitory</name>
    <pose>Unspecified</pose>
    <truncated>0</truncated>
    <Difficult>0</Difficult>
    <bndbox>
      <xmin>638</xmin>
      <ymin>167</ymin>
      <xmax>665</xmax>
      <ymax>209</ymax>
    </bndbox>
  </object>
</annotation>
