<annotation verified="yes">
  <folder>images</folder>
  <filename>01793</filename>
  <path>J:\360\5cloud\images\01793.png</path>
  <source>
    <database>Unknown</database>
  </source>
  <size>
    <width>1280</width>
    <height>720</height>
    <depth>3</depth>
  </size>
  <segmented>0</segmented>
  <object>
    <name>prohibitory</name>
    <pose>Unspecified</pose>
    <truncated>0</truncated>
    <Difficult>0</Difficult>
    <bndbox>
      <xmin>480</xmin>
      <ymin>232</ymin>
      <xmax>497</xmax>
      <ymax>251</ymax>
    </bndbox>
  </object>
  <object>
    <name>prohibitory</name>
    <pose>Unspecified</pose>
    <truncated>0</truncated>
    <Difficult>0</Difficult>
    <bndbox>
      <xmin>479</xmin>
      <ymin>255</ymin>
      <xmax>496</xmax>
      <ymax>274</ymax>
    </bndbox>
  </object>
  <object>
    <name>prohibitory</name>
    <pose>Unspecified</pose>
    <truncated>0</truncated>
    <Difficult>0</Difficult>
    <bndbox>
      <xmin>477</xmin>
      <ymin>277</ymin>
      <xmax>496</xmax>
      <ymax>295</ymax>
    </bndbox>
  </object>
</annotation>
